githyperlink/__init__.py
githyperlink/cli.py
githyperlink/main.py
githyperlink-0.1.dist-info/LICENSE
githyperlink-0.1.dist-info/METADATA
githyperlink-0.1.dist-info/WHEEL
githyperlink-0.1.dist-info/entry_points.txt
githyperlink-0.1.dist-info/top_level.txt
githyperlink-0.1.dist-info/RECORD
