Metadata-Version: 2.1
Name: githyperlink
Version: 0.1
Summary: UNKNOWN
Home-page: https://github.com/tfiers/githyperlink
Author: Tomas Fiers
Author-email: tomas.fiers@gmail.com
License: UNKNOWN
Project-URL: Source Code, https://github.com/tfiers/githyperlink
Platform: UNKNOWN
Classifier: License :: OSI Approved :: MIT License
Classifier: Programming Language :: Python :: 3
Classifier: Operating System :: OS Independent
Requires-Python: >= 3.9
License-File: LICENSE
Requires-Dist: click (>=6)
